obp/__init__.py
obp/dataset/__init__.py
obp/dataset/base.py
obp/dataset/multiclass.py
obp/dataset/obd/bts/all/all.csv
obp/dataset/obd/bts/all/item_context.csv
obp/dataset/obd/bts/men/item_context.csv
obp/dataset/obd/bts/men/men.csv
obp/dataset/obd/bts/women/item_context.csv
obp/dataset/obd/bts/women/women.csv
obp/dataset/obd/random/all/all.csv
obp/dataset/obd/random/all/item_context.csv
obp/dataset/obd/random/men/item_context.csv
obp/dataset/obd/random/men/men.csv
obp/dataset/obd/random/women/item_context.csv
obp/dataset/obd/random/women/women.csv
obp/dataset/real.py
obp/dataset/reward_type.py
obp/dataset/synthetic.py
obp/dataset/synthetic_continuous.py
obp/dataset/synthetic_embed.py
obp/dataset/synthetic_multi.py
obp/dataset/synthetic_slate.py
obp/ope/__init__.py
obp/ope/classification_model.py
obp/ope/estimators.py
obp/ope/estimators_continuous.py
obp/ope/estimators_embed.py
obp/ope/estimators_multi.py
obp/ope/estimators_slate.py
obp/ope/estimators_tuning.py
obp/ope/helper.py
obp/ope/meta.py
obp/ope/meta_continuous.py
obp/ope/meta_multi.py
obp/ope/meta_slate.py
obp/ope/regression_model.py
obp/ope/regression_model_slate.py
obp/policy/__init__.py
obp/policy/base.py
obp/policy/conf/prior_bts.yaml
obp/policy/contextfree.py
obp/policy/linear.py
obp/policy/logistic.py
obp/policy/offline.py
obp/policy/offline_continuous.py
obp/policy/policy_type.py
obp/simulator/__init__.py
obp/simulator/coefficient_drifter.py
obp/simulator/delay_sampler.py
obp/simulator/replay.py
obp/simulator/simulator.py
obp/types.py
obp/utils.py
obp/version.py
sb_obp-0.5.10.dist-info/LICENSE
sb_obp-0.5.10.dist-info/METADATA
sb_obp-0.5.10.dist-info/WHEEL
sb_obp-0.5.10.dist-info/RECORD
